gwdatafind_server/__init__.py
gwdatafind_server/_version.py
gwdatafind_server/app.py
gwdatafind_server/authentication.py
gwdatafind_server/cache.py
gwdatafind_server/config.py
gwdatafind_server/api/__init__.py
gwdatafind_server/api/base.py
gwdatafind_server/api/ldr.py
gwdatafind_server/api/utils.py
gwdatafind_server/api/v1.py
gwdatafind_server-1.5.0.dist-info/LICENSE
gwdatafind_server-1.5.0.dist-info/METADATA
gwdatafind_server-1.5.0.dist-info/WHEEL
gwdatafind_server-1.5.0.dist-info/top_level.txt
gwdatafind_server-1.5.0.dist-info/RECORD
