Metadata-Version: 2.1
Name: gwdatafind-server
Version: 1.5.0
Summary: The server library for the GWDataFind service
Home-page: https://git.ligo.org/computing/gwdatafind/server
Author: Duncan Meacher
Author-email: duncan.meacher@ligo.org
License: GPL-3.0-or-later
Project-URL: Bug Tracker, https://git.ligo.org/computing/gwdatafind/server/-/issues
Project-URL: Documentation, https://computing.docs.ligo.org/gwdatafind/server/
Project-URL: Source Code, https://git.ligo.org/computing/gwdatafind/server
Classifier: License :: OSI Approved :: GNU General Public License v3 or later (GPLv3+)
Classifier: Natural Language :: English
Classifier: Operating System :: Unix
Classifier: Programming Language :: Python
Classifier: Programming Language :: Python :: 3
Classifier: Programming Language :: Python :: 3.6
Classifier: Programming Language :: Python :: 3.7
Classifier: Programming Language :: Python :: 3.8
Classifier: Programming Language :: Python :: 3.9
Classifier: Programming Language :: Python :: 3.10
Classifier: Topic :: Scientific/Engineering
Classifier: Topic :: Scientific/Engineering :: Astronomy
Classifier: Topic :: Scientific/Engineering :: Physics
License-File: LICENSE
Requires-Dist: configobj
Requires-Dist: flask >=2.0.0
Requires-Dist: ligo-segments
Requires-Dist: scitokens
Provides-Extra: docs
Requires-Dist: mkdocs ; extra == 'docs'
Provides-Extra: test
Requires-Dist: pytest >=3.1.0 ; extra == 'test'
